pyerd/__init__.py
pyerd/constants.py
pyerd/diagrams/diagram.py
pyerd/diagrams/mermaid.py
pyerd/model_node.py
pyerd/utils.py
pyerd-0.2.0.dist-info/LICENSE
pyerd-0.2.0.dist-info/METADATA
pyerd-0.2.0.dist-info/WHEEL
pyerd-0.2.0.dist-info/RECORD
